iterfilesystem/__init__.py
iterfilesystem/benchmark.py
iterfilesystem/bin/__init__.py
iterfilesystem/bin/print_fs_stats.py
iterfilesystem/constants.py
iterfilesystem/example.py
iterfilesystem/humanize.py
iterfilesystem/iter_scandir.py
iterfilesystem/main.py
iterfilesystem/process_bar.py
iterfilesystem/process_priority.py
iterfilesystem/publish.py
iterfilesystem/statistic_helper.py
iterfilesystem/tests/__init__.py
iterfilesystem/tests/test_base_test_case.py
iterfilesystem/tests/test_cli.py
iterfilesystem/tests/test_example.py
iterfilesystem/tests/test_iter_filesystem.py
iterfilesystem/tests/test_project_setup.py
iterfilesystem/tests/test_scandir_walker.py
iterfilesystem/tests/test_utils.py
iterfilesystem/utils.py
iterfilesystem-1.4.3.dist-info/entry_points.txt
iterfilesystem-1.4.3.dist-info/LICENSE
iterfilesystem-1.4.3.dist-info/WHEEL
iterfilesystem-1.4.3.dist-info/METADATA
iterfilesystem-1.4.3.dist-info/RECORD
